Metadata-Version: 2.1
Name: ipasymbols
Version: 0.1.0
Summary: Properties of IPA symbols for data analysis.
Home-page: http://github.com/ulf1/ipasymbols
Author: Ulf Hamster
Author-email: 554c46@gmail.com
License: Apache License 2.0
Platform: UNKNOWN
Requires-Python: >=3.6
License-File: LICENSE
